setup.py
egen111222_tmp_fast_project.egg-info/PKG-INFO
egen111222_tmp_fast_project.egg-info/SOURCES.txt
egen111222_tmp_fast_project.egg-info/dependency_links.txt
egen111222_tmp_fast_project.egg-info/top_level.txt
my_project/program.py