Metadata-Version: 2.1
Name: egen111222-tmp-fast-project
Version: 1.0
Summary: Python Distribution Utilities
Home-page: https://www.python.org/sigs/distutils-sig/
Author: Kirill
Author-email: egen13@ukr.net
License: UNKNOWN
Platform: UNKNOWN
